gmag/__init__.py
gmag/_print_util.py
gmag/galaxy.py
gmag/sdss.py
gmag-2.1.6.dist-info/LICENSE.txt
gmag-2.1.6.dist-info/METADATA
gmag-2.1.6.dist-info/WHEEL
gmag-2.1.6.dist-info/top_level.txt
gmag-2.1.6.dist-info/RECORD
