Metadata-Version: 2.1
Name: gmag
Version: 2.1.6
Summary: Give Me A Galaxy! | Fast SDSS Galaxy Image Download
Author: Junyu Chen
License: MIT License
Project-URL: Repository, https://github.com/Junyu474/GMAG
Project-URL: Documentation, https://junyu474.github.io/GMAG/index.html
Keywords: astronomy,sdss,fits,galaxy,image processing
Classifier: Programming Language :: Python :: 3
Classifier: License :: OSI Approved :: MIT License
Classifier: Topic :: Scientific/Engineering :: Astronomy
Classifier: Topic :: Scientific/Engineering :: Image Processing
Requires-Python: >=3.7
License-File: LICENSE.txt
Requires-Dist: numpy (>=1.18)
Requires-Dist: astropy (>=4.0)
Requires-Dist: matplotlib (>=3.2)
Requires-Dist: requests (>=2.23)
Requires-Dist: tqdm (>=4.48)
Requires-Dist: jupyter (>=1.0)
Provides-Extra: build
Requires-Dist: build ; extra == 'build'
Requires-Dist: twine ; extra == 'build'
Requires-Dist: pdoc3 ; extra == 'build'
Provides-Extra: dev
Requires-Dist: black ; extra == 'dev'
